otp_agents/__init__.py
otp_agents/admin.py
otp_agents/apps.py
otp_agents/decorators.py
otp_agents/forms.py
otp_agents/tests.py
otp_agents/views.py
otp_agents/test/__init__.py
otp_agents/test/urls.py
otp_agents/test/views.py
django_otp_agents-1.1.0.dist-info/METADATA
django_otp_agents-1.1.0.dist-info/WHEEL
django_otp_agents-1.1.0.dist-info/licenses/LICENSE
django_otp_agents-1.1.0.dist-info/RECORD
