Metadata-Version: 2.4
Name: django-otp-agents
Version: 1.1.0
Summary: Integration of django-otp and django-agent-trust.
Project-URL: Homepage, https://github.com/django-otp/django-otp-agents
Project-URL: Documentation, https://django-otp-agents.readthedocs.io/
Author-email: Peter Sagerson <psagers@ignorare.net>
License-Expression: Unlicense
License-File: LICENSE
Classifier: Development Status :: 5 - Production/Stable
Classifier: Framework :: Django
Classifier: Framework :: Django :: 4.2
Classifier: Framework :: Django :: 5.1
Classifier: Framework :: Django :: 5.2
Classifier: Intended Audience :: Developers
Classifier: License :: OSI Approved :: The Unlicense (Unlicense)
Classifier: Programming Language :: Python :: 3
Classifier: Programming Language :: Python :: 3 :: Only
Classifier: Topic :: Security
Classifier: Topic :: Software Development :: Libraries :: Python Modules
Requires-Python: >=3.7
Requires-Dist: django-agent-trust~=1.0
Requires-Dist: django-otp~=1.0
